aiomodbus/__init__.py
aiomodbus/crc.py
aiomodbus/decoders.py
aiomodbus/encoders.py
aiomodbus/exceptions.py
aiomodbus/serial.py
aiomodbus/tcp.py
aiomodbus-0.6.0.dist-info/LICENSE
aiomodbus-0.6.0.dist-info/METADATA
aiomodbus-0.6.0.dist-info/WHEEL
aiomodbus-0.6.0.dist-info/top_level.txt
aiomodbus-0.6.0.dist-info/RECORD
