Metadata-Version: 2.1
Name: aiomodbus
Version: 0.6.0
Summary: Lightweight Modbus library using asyncio
Author: Ryan Parry-Jones
Author-email: ryanspj+github@gmail.com
Classifier: Intended Audience :: Manufacturing
Classifier: Intended Audience :: Telecommunications Industry
Classifier: Operating System :: OS Independent
Classifier: Programming Language :: Python :: 3 :: Only
Classifier: Programming Language :: Python :: 3.7
Classifier: Programming Language :: Python :: 3.8
Classifier: Programming Language :: Python :: 3.9
Classifier: Programming Language :: Python :: 3.10
Classifier: Programming Language :: Python :: 3.11
Classifier: Development Status :: 2 - Pre-Alpha
Requires-Python: >=3.7
License-File: LICENSE
Requires-Dist: pyserial-asyncio
